LICENSE.txt
MANIFEST.in
README.rst
space_aliens/__init__.py
space_aliens/audio.py
space_aliens/main.py
space_aliens/menu.py
space_aliens/util.py
space_aliens.egg-info/PKG-INFO
space_aliens.egg-info/SOURCES.txt
space_aliens.egg-info/dependency_links.txt
space_aliens.egg-info/requires.txt
space_aliens.egg-info/top_level.txt
space_aliens/data/Thumbs.db
space_aliens/data/background.png
space_aliens/data/boom.wav
space_aliens/data/cruiser.png
space_aliens/data/enemy_ship.png
space_aliens/data/fast_bg.ogg
space_aliens/data/flaunch.wav
space_aliens/data/freesansbold.ttf
space_aliens/data/icon.ico
space_aliens/data/laser_green.png
space_aliens/data/laser_red.png
space_aliens/data/player.png
space_aliens/data/player_left.png
space_aliens/data/player_right.png
space_aliens/data/shield.png
space_aliens/data/slow_bg.ogg
space_aliens/data/sound_off.png
space_aliens/data/sound_on.png
space_aliens/data/star_yellow.png
space_aliens/data/explosion_red/0016.png
space_aliens/data/explosion_red/0017.png
space_aliens/data/explosion_red/0018.png
space_aliens/data/explosion_red/0019.png
space_aliens/data/explosion_red/0020.png
space_aliens/data/explosion_red/0021.png
space_aliens/data/explosion_red/0022.png
space_aliens/data/explosion_red/0023.png
space_aliens/data/explosion_red/0024.png
space_aliens/data/explosion_red/0025.png
space_aliens/data/explosion_red/0026.png
space_aliens/data/explosion_red/0027.png
space_aliens/data/explosion_red/0028.png
space_aliens/data/explosion_red/0029.png
space_aliens/data/explosion_red/0030.png