Metadata-Version: 1.1
Name: space-aliens
Version: 1.2
Summary: top-down space shooter
Home-page: http://semicoded.com/
Author: semicoded
Author-email: admin@semicoded.com
License: BSD 2-Clause License
Keywords: game space aliens arcade shooter
Platform: UNKNOWN
Classifier: Development Status :: 5 - Production/Stable
Classifier: Intended Audience :: Developers
Classifier: Intended Audience :: End Users/Desktop
Classifier: License :: OSI Approved :: BSD License
Classifier: Operating System :: Microsoft :: Windows
Classifier: Programming Language :: Python :: 3
Classifier: Programming Language :: Python :: 3.4
Classifier: Topic :: Games/Entertainment
Classifier: Topic :: Games/Entertainment :: Arcade
